lambdaorm/__init__.py
lambdaorm/application.py
lambdaorm/domain.py
lambdaorm/infrastructure.py
lambdaorm/test_execute.py
lambdaorm-0.0.1.dist-info/LICENSE
lambdaorm-0.0.1.dist-info/METADATA
lambdaorm-0.0.1.dist-info/WHEEL
lambdaorm-0.0.1.dist-info/top_level.txt
lambdaorm-0.0.1.dist-info/RECORD
